daita/__init__.py
daita/agents/__init__.py
daita/agents/agent.py
daita/agents/base.py
daita/cli/__init__.py
daita/cli/__main__.py
daita/cli/ascii_art.py
daita/cli/main.py
daita/cli/utils.py
daita/cli/core/__init__.py
daita/cli/core/create.py
daita/cli/core/deploy.py
daita/cli/core/deployments.py
daita/cli/core/import_detector.py
daita/cli/core/init.py
daita/cli/core/logs.py
daita/cli/core/managed_deploy.py
daita/cli/core/run.py
daita/cli/core/status.py
daita/cli/core/test.py
daita/cli/core/webhooks.py
daita/config/__init__.py
daita/config/base.py
daita/config/settings.py
daita/core/__init__.py
daita/core/decision_tracing.py
daita/core/exceptions.py
daita/core/focus.py
daita/core/interfaces.py
daita/core/plugin_tracing.py
daita/core/relay.py
daita/core/reliability.py
daita/core/scaling.py
daita/core/streaming.py
daita/core/tools.py
daita/core/tracing.py
daita/core/workflow.py
daita/display/__init__.py
daita/display/console.py
daita/execution/__init__.py
daita/execution/client.py
daita/execution/exceptions.py
daita/execution/models.py
daita/llm/__init__.py
daita/llm/anthropic.py
daita/llm/base.py
daita/llm/factory.py
daita/llm/gemini.py
daita/llm/grok.py
daita/llm/mock.py
daita/llm/openai.py
daita/plugins/__init__.py
daita/plugins/base.py
daita/plugins/base_db.py
daita/plugins/base_vector.py
daita/plugins/catalog.py
daita/plugins/chroma.py
daita/plugins/elasticsearch.py
daita/plugins/lineage.py
daita/plugins/mcp.py
daita/plugins/mongodb.py
daita/plugins/mysql.py
daita/plugins/neo4j_graph.py
daita/plugins/orchestrator.py
daita/plugins/pinecone.py
daita/plugins/postgresql.py
daita/plugins/qdrant.py
daita/plugins/redis_messaging.py
daita/plugins/rest.py
daita/plugins/s3.py
daita/plugins/slack.py
daita/plugins/snowflake.py
daita/plugins/websearch.py
daita/utils/__init__.py
daita_agents-0.6.2.dist-info/licenses/LICENSE
daita_agents-0.6.2.dist-info/METADATA
daita_agents-0.6.2.dist-info/WHEEL
daita_agents-0.6.2.dist-info/entry_points.txt
daita_agents-0.6.2.dist-info/top_level.txt
daita_agents-0.6.2.dist-info/RECORD
