Metadata-Version: 2.4
Name: daita-agents
Version: 0.6.2
Summary: Daita Agents - Data focused AI agent framework with free local use and premium hosted enterprise features
Author-email: Daita <support@daita-tech.io>
License: Proprietary
Project-URL: Homepage, https://daita-tech.io
Project-URL: Documentation, https://docs.daita-tech.io
Keywords: ai,agents,llm,automation,workflows,sdk
Classifier: Development Status :: 4 - Beta
Classifier: Intended Audience :: Developers
Classifier: License :: Other/Proprietary License
Classifier: Programming Language :: Python :: 3
Classifier: Programming Language :: Python :: 3.11
Classifier: Programming Language :: Python :: 3.12
Classifier: Topic :: Scientific/Engineering :: Artificial Intelligence
Requires-Python: >=3.11
License-File: LICENSE
Requires-Dist: pydantic>=2.0.0
Requires-Dist: aiohttp>=3.8.0
Requires-Dist: python-dotenv>=1.0.0
Requires-Dist: click>=8.0.0
Requires-Dist: watchdog>=3.0.0
Requires-Dist: PyYAML>=6.0.0
Requires-Dist: croniter>=1.0.0
Requires-Dist: aiofiles>=24.1.0
Requires-Dist: openai>=1.0.0
Requires-Dist: certifi>=2025.4.0
Requires-Dist: PyJWT>=2.10.0
Provides-Extra: recommended
Requires-Dist: anthropic>=0.5.0; extra == "recommended"
Requires-Dist: pandas>=1.5.0; extra == "recommended"
Requires-Dist: numpy>=1.20.0; extra == "recommended"
Requires-Dist: beautifulsoup4>=4.13.0; extra == "recommended"
Requires-Dist: lxml>=5.4.0; extra == "recommended"
Provides-Extra: data
Requires-Dist: pandas>=1.5.0; extra == "data"
Requires-Dist: numpy>=1.20.0; extra == "data"
Requires-Dist: openpyxl>=3.1.0; extra == "data"
Requires-Dist: beautifulsoup4>=4.13.0; extra == "data"
Requires-Dist: lxml>=5.4.0; extra == "data"
Requires-Dist: jsonpath-ng>=1.7.0; extra == "data"
Requires-Dist: fuzzywuzzy>=0.18.0; extra == "data"
Requires-Dist: psycopg2-binary>=2.9.0; extra == "data"
Requires-Dist: asyncpg>=0.27.0; extra == "data"
Provides-Extra: production
Requires-Dist: boto3>=1.38.0; extra == "production"
Requires-Dist: psutil>=7.0.0; extra == "production"
Requires-Dist: fastapi>=0.115.0; extra == "production"
Requires-Dist: uvicorn>=0.34.0; extra == "production"
Provides-Extra: anthropic
Requires-Dist: anthropic>=0.5.0; extra == "anthropic"
Provides-Extra: google
Requires-Dist: google-genai>=0.3.0; extra == "google"
Provides-Extra: transformers
Requires-Dist: transformers>=4.51.0; extra == "transformers"
Provides-Extra: llm-all
Requires-Dist: anthropic>=0.5.0; extra == "llm-all"
Requires-Dist: google-genai>=0.3.0; extra == "llm-all"
Provides-Extra: postgresql
Requires-Dist: asyncpg>=0.27.0; extra == "postgresql"
Requires-Dist: psycopg2-binary>=2.9.0; extra == "postgresql"
Provides-Extra: mysql
Requires-Dist: aiomysql>=0.2.0; extra == "mysql"
Requires-Dist: SQLAlchemy>=2.0.0; extra == "mysql"
Provides-Extra: mongodb
Requires-Dist: motor>=3.0.0; extra == "mongodb"
Provides-Extra: sqlite
Requires-Dist: aiosqlite>=0.21.0; extra == "sqlite"
Requires-Dist: SQLAlchemy>=2.0.0; extra == "sqlite"
Provides-Extra: snowflake
Requires-Dist: snowflake-connector-python>=3.0.0; extra == "snowflake"
Provides-Extra: elasticsearch
Requires-Dist: elasticsearch>=8.0.0; extra == "elasticsearch"
Provides-Extra: databases
Requires-Dist: asyncpg>=0.27.0; extra == "databases"
Requires-Dist: psycopg2-binary>=2.9.0; extra == "databases"
Requires-Dist: aiomysql>=0.2.0; extra == "databases"
Requires-Dist: SQLAlchemy>=2.0.0; extra == "databases"
Requires-Dist: motor>=3.0.0; extra == "databases"
Requires-Dist: aiosqlite>=0.21.0; extra == "databases"
Requires-Dist: snowflake-connector-python>=3.0.0; extra == "databases"
Requires-Dist: elasticsearch>=8.0.0; extra == "databases"
Provides-Extra: chromadb
Requires-Dist: chromadb>=1.3.0; extra == "chromadb"
Provides-Extra: pinecone
Requires-Dist: pinecone>=5.0.0; extra == "pinecone"
Provides-Extra: qdrant
Requires-Dist: qdrant-client>=1.16.0; extra == "qdrant"
Provides-Extra: vectordb
Requires-Dist: chromadb>=1.3.0; extra == "vectordb"
Requires-Dist: pinecone>=5.0.0; extra == "vectordb"
Requires-Dist: qdrant-client>=1.16.0; extra == "vectordb"
Provides-Extra: aws
Requires-Dist: boto3>=1.38.0; extra == "aws"
Provides-Extra: slack
Requires-Dist: slack-sdk>=3.31.0; extra == "slack"
Provides-Extra: mcp
Requires-Dist: mcp>=1.0.0; extra == "mcp"
Provides-Extra: cloud
Requires-Dist: boto3>=1.38.0; extra == "cloud"
Requires-Dist: slack-sdk>=3.31.0; extra == "cloud"
Provides-Extra: web
Requires-Dist: beautifulsoup4>=4.13.0; extra == "web"
Requires-Dist: lxml>=5.4.0; extra == "web"
Provides-Extra: api-server
Requires-Dist: fastapi>=0.115.0; extra == "api-server"
Requires-Dist: uvicorn>=0.34.0; extra == "api-server"
Requires-Dist: python-multipart>=0.0.20; extra == "api-server"
Provides-Extra: websearch
Requires-Dist: tavily-python>=0.3.0; extra == "websearch"
Provides-Extra: complete
Requires-Dist: anthropic>=0.5.0; extra == "complete"
Requires-Dist: google-genai>=0.3.0; extra == "complete"
Requires-Dist: asyncpg>=0.27.0; extra == "complete"
Requires-Dist: psycopg2-binary>=2.9.0; extra == "complete"
Requires-Dist: SQLAlchemy>=2.0.0; extra == "complete"
Requires-Dist: pandas>=1.5.0; extra == "complete"
Requires-Dist: numpy>=1.20.0; extra == "complete"
Requires-Dist: beautifulsoup4>=4.13.0; extra == "complete"
Requires-Dist: lxml>=5.4.0; extra == "complete"
Requires-Dist: jsonpath-ng>=1.7.0; extra == "complete"
Requires-Dist: tavily-python>=0.3.0; extra == "complete"
Requires-Dist: boto3>=1.38.0; extra == "complete"
Requires-Dist: slack-sdk>=3.31.0; extra == "complete"
Requires-Dist: psutil>=7.0.0; extra == "complete"
Provides-Extra: all
Requires-Dist: anthropic>=0.5.0; extra == "all"
Requires-Dist: google-genai>=0.3.0; extra == "all"
Requires-Dist: transformers>=4.51.0; extra == "all"
Requires-Dist: asyncpg>=0.27.0; extra == "all"
Requires-Dist: psycopg2-binary>=2.9.0; extra == "all"
Requires-Dist: aiomysql>=0.2.0; extra == "all"
Requires-Dist: SQLAlchemy>=2.0.0; extra == "all"
Requires-Dist: motor>=3.0.0; extra == "all"
Requires-Dist: aiosqlite>=0.21.0; extra == "all"
Requires-Dist: snowflake-connector-python>=3.0.0; extra == "all"
Requires-Dist: elasticsearch>=8.0.0; extra == "all"
Requires-Dist: chromadb>=1.3.0; extra == "all"
Requires-Dist: pinecone>=5.0.0; extra == "all"
Requires-Dist: qdrant-client>=1.16.0; extra == "all"
Requires-Dist: boto3>=1.38.0; extra == "all"
Requires-Dist: slack-sdk>=3.31.0; extra == "all"
Requires-Dist: mcp>=1.0.0; extra == "all"
Requires-Dist: pandas>=1.5.0; extra == "all"
Requires-Dist: numpy>=1.20.0; extra == "all"
Requires-Dist: openpyxl>=3.1.0; extra == "all"
Requires-Dist: beautifulsoup4>=4.13.0; extra == "all"
Requires-Dist: lxml>=5.4.0; extra == "all"
Requires-Dist: jsonpath-ng>=1.7.0; extra == "all"
Requires-Dist: fuzzywuzzy>=0.18.0; extra == "all"
Requires-Dist: tavily-python>=0.3.0; extra == "all"
Requires-Dist: fastapi>=0.115.0; extra == "all"
Requires-Dist: uvicorn>=0.34.0; extra == "all"
Requires-Dist: python-multipart>=0.0.20; extra == "all"
Requires-Dist: psutil>=7.0.0; extra == "all"
Provides-Extra: dev
Requires-Dist: pytest>=8.0.0; extra == "dev"
Requires-Dist: pytest-asyncio>=0.26.0; extra == "dev"
Requires-Dist: pytest-cov>=4.1.0; extra == "dev"
Requires-Dist: black>=23.0.0; extra == "dev"
Requires-Dist: mypy>=1.4.0; extra == "dev"
Dynamic: license-file
